{
  "version": "3.3.0-beta",
  "flags": {},
  "shapes": [
    {
      "label": "tube",
      "score": null,
      "points": [
        [
          228.0,
          177.0
        ],
        [
          227.0,
          178.0
        ],
        [
          226.0,
          178.0
        ],
        [
          223.0,
          181.0
        ],
        [
          223.0,
          211.0
        ],
        [
          224.0,
          212.0
        ],
        [
          224.0,
          214.0
        ],
        [
          225.0,
          215.0
        ],
        [
          225.0,
          217.0
        ],
        [
          226.0,
          218.0
        ],
        [
          226.0,
          220.0
        ],
        [
          228.0,
          222.0
        ],
        [
          228.0,
          223.0
        ],
        [
          229.0,
          224.0
        ],
        [
          230.0,
          224.0
        ],
        [
          231.0,
          225.0
        ],
        [
          235.0,
          225.0
        ],
        [
          236.0,
          224.0
        ],
        [
          237.0,
          224.0
        ],
        [
          238.0,
          223.0
        ],
        [
          238.0,
          222.0
        ],
        [
          239.0,
          221.0
        ],
        [
          239.0,
          220.0
        ],
        [
          240.0,
          219.0
        ],
        [
          240.0,
          218.0
        ],
        [
          242.0,
          216.0
        ],
        [
          242.0,
          215.0
        ],
        [
          243.0,
          214.0
        ],
        [
          243.0,
          198.0
        ],
        [
          242.0,
          197.0
        ],
        [
          243.0,
          196.0
        ],
        [
          243.0,
          183.0
        ],
        [
          242.0,
          182.0
        ],
        [
          242.0,
          180.0
        ],
        [
          240.0,
          178.0
        ],
        [
          238.0,
          178.0
        ],
        [
          237.0,
          177.0
        ]
      ],
      "group_id": null,
      "description": "",
      "difficult": false,
      "shape_type": "polygon",
      "flags": {},
      "attributes": {},
      "kie_linking": []
    },
    {
      "label": "tube",
      "score": null,
      "points": [
        [
          293.0,
          221.0
        ],
        [
          292.0,
          222.0
        ],
        [
          290.0,
          222.0
        ],
        [
          289.0,
          223.0
        ],
        [
          288.0,
          223.0
        ],
        [
          286.0,
          225.0
        ],
        [
          286.0,
          226.0
        ],
        [
          285.0,
          227.0
        ],
        [
          285.0,
          254.0
        ],
        [
          286.0,
          255.0
        ],
        [
          286.0,
          261.0
        ],
        [
          288.0,
          263.0
        ],
        [
          288.0,
          264.0
        ],
        [
          289.0,
          265.0
        ],
        [
          289.0,
          268.0
        ],
        [
          292.0,
          271.0
        ],
        [
          299.0,
          271.0
        ],
        [
          300.0,
          270.0
        ],
        [
          300.0,
          269.0
        ],
        [
          301.0,
          268.0
        ],
        [
          301.0,
          267.0
        ],
        [
          303.0,
          265.0
        ],
        [
          303.0,
          264.0
        ],
        [
          304.0,
          263.0
        ],
        [
          304.0,
          261.0
        ],
        [
          305.0,
          260.0
        ],
        [
          305.0,
          255.0
        ],
        [
          306.0,
          254.0
        ],
        [
          306.0,
          234.0
        ],
        [
          307.0,
          233.0
        ],
        [
          307.0,
          230.0
        ],
        [
          306.0,
          229.0
        ],
        [
          306.0,
          226.0
        ],
        [
          302.0,
          222.0
        ],
        [
          299.0,
          222.0
        ],
        [
          298.0,
          221.0
        ]
      ],
      "group_id": null,
      "description": "",
      "difficult": false,
      "shape_type": "polygon",
      "flags": {},
      "attributes": {},
      "kie_linking": []
    },
    {
      "label": "tube",
      "score": null,
      "points": [
        [
          290.0,
          273.0
        ],
        [
          289.0,
          274.0
        ],
        [
          288.0,
          274.0
        ],
        [
          287.0,
          275.0
        ],
        [
          286.0,
          275.0
        ],
        [
          285.0,
          276.0
        ],
        [
          285.0,
          277.0
        ],
        [
          284.0,
          278.0
        ],
        [
          284.0,
          280.0
        ],
        [
          283.0,
          281.0
        ],
        [
          283.0,
          308.0
        ],
        [
          284.0,
          309.0
        ],
        [
          284.0,
          313.0
        ],
        [
          285.0,
          314.0
        ],
        [
          285.0,
          315.0
        ],
        [
          286.0,
          316.0
        ],
        [
          286.0,
          318.0
        ],
        [
          287.0,
          319.0
        ],
        [
          287.0,
          320.0
        ],
        [
          291.0,
          324.0
        ],
        [
          292.0,
          324.0
        ],
        [
          293.0,
          325.0
        ],
        [
          295.0,
          325.0
        ],
        [
          296.0,
          326.0
        ],
        [
          297.0,
          325.0
        ],
        [
          298.0,
          325.0
        ],
        [
          301.0,
          322.0
        ],
        [
          301.0,
          321.0
        ],
        [
          302.0,
          320.0
        ],
        [
          302.0,
          319.0
        ],
        [
          303.0,
          318.0
        ],
        [
          303.0,
          316.0
        ],
        [
          305.0,
          314.0
        ],
        [
          305.0,
          308.0
        ],
        [
          306.0,
          307.0
        ],
        [
          306.0,
          288.0
        ],
        [
          307.0,
          287.0
        ],
        [
          307.0,
          280.0
        ],
        [
          306.0,
          279.0
        ],
        [
          306.0,
          278.0
        ],
        [
          305.0,
          277.0
        ],
        [
          305.0,
          276.0
        ],
        [
          304.0,
          276.0
        ],
        [
          302.0,
          274.0
        ],
        [
          301.0,
          274.0
        ],
        [
          300.0,
          273.0
        ]
      ],
      "group_id": null,
      "description": "",
      "difficult": false,
      "shape_type": "polygon",
      "flags": {},
      "attributes": {},
      "kie_linking": []
    },
    {
      "label": "tube",
      "score": null,
      "points": [
        [
          290.0,
          335.0
        ],
        [
          289.0,
          336.0
        ],
        [
          287.0,
          336.0
        ],
        [
          282.0,
          341.0
        ],
        [
          282.0,
          343.0
        ],
        [
          281.0,
          344.0
        ],
        [
          281.0,
          354.0
        ],
        [
          282.0,
          355.0
        ],
        [
          282.0,
          358.0
        ],
        [
          281.0,
          359.0
        ],
        [
          281.0,
          363.0
        ],
        [
          282.0,
          364.0
        ],
        [
          282.0,
          376.0
        ],
        [
          283.0,
          377.0
        ],
        [
          283.0,
          379.0
        ],
        [
          284.0,
          380.0
        ],
        [
          284.0,
          381.0
        ],
        [
          286.0,
          383.0
        ],
        [
          286.0,
          385.0
        ],
        [
          288.0,
          387.0
        ],
        [
          289.0,
          387.0
        ],
        [
          290.0,
          388.0
        ],
        [
          295.0,
          388.0
        ],
        [
          296.0,
          389.0
        ],
        [
          297.0,
          388.0
        ],
        [
          299.0,
          388.0
        ],
        [
          302.0,
          385.0
        ],
        [
          302.0,
          384.0
        ],
        [
          303.0,
          383.0
        ],
        [
          303.0,
          382.0
        ],
        [
          304.0,
          381.0
        ],
        [
          304.0,
          380.0
        ],
        [
          305.0,
          379.0
        ],
        [
          305.0,
          378.0
        ],
        [
          306.0,
          377.0
        ],
        [
          306.0,
          374.0
        ],
        [
          307.0,
          373.0
        ],
        [
          307.0,
          360.0
        ],
        [
          308.0,
          359.0
        ],
        [
          308.0,
          345.0
        ],
        [
          307.0,
          344.0
        ],
        [
          307.0,
          342.0
        ],
        [
          306.0,
          341.0
        ],
        [
          306.0,
          340.0
        ],
        [
          303.0,
          337.0
        ],
        [
          302.0,
          337.0
        ],
        [
          301.0,
          336.0
        ],
        [
          300.0,
          336.0
        ],
        [
          299.0,
          335.0
        ]
      ],
      "group_id": null,
      "description": "",
      "difficult": false,
      "shape_type": "polygon",
      "flags": {},
      "attributes": {},
      "kie_linking": []
    }
  ],
  "imagePath": "28.jpg",
  "imageData": null,
  "imageHeight": 480,
  "imageWidth": 640
}